indexly/__init__.py
indexly/__main__.py
indexly/analysis_orchestrator.py
indexly/analysis_result.py
indexly/analyze_db.py
indexly/analyze_json.py
indexly/analyze_utils.py
indexly/analyze_xml.py
indexly/cache_utils.py
indexly/changelog.json
indexly/clean_csv.py
indexly/cli_utils.py
indexly/config.py
indexly/csv_analyzer.py
indexly/csv_pipeline.py
indexly/datetime_utils.py
indexly/db_detect.py
indexly/db_inspector.py
indexly/db_pipeline.py
indexly/db_schema_utils.py
indexly/db_summary_indexly.py
indexly/db_update.py
indexly/db_utils.py
indexly/debug.py
indexly/debug_tbl.py
indexly/doctor.py
indexly/excel_pipeline.py
indexly/export_utils.py
indexly/extract_utils.py
indexly/filetype_utils.py
indexly/fts_core.py
indexly/indexly.py
indexly/indexly_detector.py
indexly/json_cache_normalizer.py
indexly/json_pipeline.py
indexly/license_utils.py
indexly/log_utils.py
indexly/mermaid_diagram.py
indexly/migrate_db.py
indexly/migration_manager.py
indexly/mtw_extractor.py
indexly/output_utils.py
indexly/parquet_pipeline.py
indexly/path_utils.py
indexly/persist.py
indexly/profiler_utils.py
indexly/profiles.py
indexly/read_indexly_json.py
indexly/relation_detector.py
indexly/rename_utils.py
indexly/ripple.py
indexly/search_core.py
indexly/semantic_index.py
indexly/table_profiler.py
indexly/test_bin_dist.py
indexly/test_near_distance.py
indexly/timeseries_utils.py
indexly/universal_loader.py
indexly/update_utils.py
indexly/utils.py
indexly/visualize_csv.py
indexly/visualize_json.py
indexly/visualize_timeseries.py
indexly/watcher.py
indexly/xml_pipeline.py
indexly/yaml_pipeline.py
indexly/assets/csv/sample_data.csv
indexly/assets/fonts/DejaVuSans-Bold.pkl
indexly/assets/fonts/DejaVuSans-Bold.ttf
indexly/assets/fonts/DejaVuSans-Oblique.pkl
indexly/assets/fonts/DejaVuSans-Oblique.ttf
indexly/assets/fonts/DejaVuSans.pkl
indexly/assets/fonts/DejaVuSans.ttf
indexly/backup/__init__.py
indexly/backup/auto.py
indexly/backup/cli.py
indexly/backup/cli_restore.py
indexly/backup/compress.py
indexly-1.2.0.dist-info/METADATA
indexly-1.2.0.dist-info/WHEEL
indexly-1.2.0.dist-info/entry_points.txt
indexly-1.2.0.dist-info/licenses/LICENSE.txt
indexly-1.2.0.dist-info/RECORD
